setup.py
squisher.py
squisher.egg-info/PKG-INFO
squisher.egg-info/SOURCES.txt
squisher.egg-info/dependency_links.txt
squisher.egg-info/top_level.txt
