Metadata-Version: 1.0
Name: squisher
Version: 0.3
Summary: "squish" Python packages into importable stand-alone .pyc files
Home-page: UNKNOWN
Author: Adam Atlas
Author-email: adam@atlas.st
License: BSD
Platform: UNKNOWN
Classifier: Development Status :: 4 - Beta
Classifier: Environment :: Console
Classifier: Intended Audience :: Developers
Classifier: License :: OSI Approved :: BSD License
Classifier: Natural Language :: English
Classifier: Programming Language :: Python
Classifier: Topic :: Software Development :: Build Tools
